safefork/__init__.py
safefork/_safefork.py
safefork-1.0.0.dist-info/METADATA
safefork-1.0.0.dist-info/WHEEL
safefork-1.0.0.dist-info/licenses/LICENSE.txt
safefork-1.0.0.dist-info/RECORD
