Metadata-Version: 2.3
Name: safefork
Version: 1.0.0
Summary: Utilities for safely forking a process
Project-URL: Documentation, https://github.com/vivster7/safefork#readme
Project-URL: Issues, https://github.com/vivster7/safefork/issues
Project-URL: Source, https://github.com/vivster7/safefork
Author-email: Vivek Dasari <vivster7@gmail.com>
License-Expression: MIT
License-File: LICENSE.txt
Keywords: fork,process,python,safe
Classifier: Development Status :: 4 - Beta
Classifier: Programming Language :: Python
Classifier: Programming Language :: Python :: 3.8
Classifier: Programming Language :: Python :: 3.9
Classifier: Programming Language :: Python :: 3.10
Classifier: Programming Language :: Python :: 3.11
Classifier: Programming Language :: Python :: 3.12
Classifier: Programming Language :: Python :: Implementation :: CPython
Classifier: Programming Language :: Python :: Implementation :: PyPy
Requires-Python: >=3.8
